urban_system_generator-0.1.1.dist-info/licenses/LICENSE
usg/__init__.py
usg/cli.py
usg/geojson_processor.py
usg/inference.py
usg/model.py
usg/postprocessor.py
usg/resources/model_attributes.py
usg/resources/postprocessor/consistency_rules.json
usg/resources/postprocessor/options_lookup.tsv
usg/resources/pretrained_model/adaptive_model_1.keras
usg/resources/pretrained_model/cat_scaler.pkl
usg/resources/pretrained_model/encoding_mapper.json
usg/resources/pretrained_model/num_scaler.pkl
urban_system_generator-0.1.1.dist-info/METADATA
urban_system_generator-0.1.1.dist-info/WHEEL
urban_system_generator-0.1.1.dist-info/entry_points.txt
urban_system_generator-0.1.1.dist-info/top_level.txt
urban_system_generator-0.1.1.dist-info/RECORD
