Metadata-Version: 2.4
Name: urban-system-generator
Version: 0.1.1
Summary: Machine learning tool for completing building attributes in urban energy models with URBANopt-BuildStock post-processing
Author-email: Rawad El Kontar <rawad.elkontar@nlr.gov>
Maintainer-email: Rawad El Kontar <rawad.elkontar@nlr.gov>
License: BSD 3-Clause License
Project-URL: Homepage, https://github.com/NatLabRockies/urban-system-generator
Project-URL: Repository, https://github.com/NatLabRockies/urban-system-generator
Project-URL: Documentation, https://github.com/NatLabRockies/urban-system-generator#readme
Project-URL: Bug Tracker, https://github.com/NatLabRockies/urban-system-generator/issues
Keywords: urban,energy,buildings,machine-learning,artificial-intelligence,GenAI,data-completion,URBANopt,BuildStock
Classifier: Development Status :: 3 - Alpha
Classifier: Intended Audience :: Science/Research
Classifier: License :: OSI Approved :: BSD License
Classifier: Programming Language :: Python :: 3
Classifier: Programming Language :: Python :: 3.8
Classifier: Programming Language :: Python :: 3.9
Classifier: Programming Language :: Python :: 3.10
Classifier: Programming Language :: Python :: 3.11
Classifier: Programming Language :: Python :: 3.12
Classifier: Topic :: Scientific/Engineering
Requires-Python: >=3.8
License-File: LICENSE
Requires-Dist: numpy>=1.21.0
Requires-Dist: pandas>=1.3.0
Requires-Dist: tensorflow>=2.10.0
Requires-Dist: scikit-learn>=1.0.0
Requires-Dist: click>=8.0.0
Provides-Extra: dev
Requires-Dist: pytest>=7.0.0; extra == "dev"
Requires-Dist: pytest-cov>=3.0.0; extra == "dev"
Requires-Dist: black>=22.0.0; extra == "dev"
Requires-Dist: flake8>=4.0.0; extra == "dev"
Requires-Dist: build; extra == "dev"
Requires-Dist: twine; extra == "dev"
Provides-Extra: docs
Requires-Dist: sphinx>=4.0.0; extra == "docs"
Requires-Dist: sphinx-rtd-theme>=1.0.0; extra == "docs"
Dynamic: license-file
